setup.py
ipyp_2d_matrix/Matrix2D.py
ipyp_2d_matrix/__init__.py
ipyp_2d_matrix.egg-info/PKG-INFO
ipyp_2d_matrix.egg-info/SOURCES.txt
ipyp_2d_matrix.egg-info/dependency_links.txt
ipyp_2d_matrix.egg-info/not-zip-safe
ipyp_2d_matrix.egg-info/top_level.txt