Metadata-Version: 1.0
Name: ipyp-2d-matrix
Version: 1.0.0.dev1
Summary: Simple 2D Matrix Class based on python list, similar to MATLAB
Home-page: UNKNOWN
Author: UNKNOWN
Author-email: UNKNOWN
License: UNKNOWN
Platform: UNKNOWN
